photoprism/__init__.py
photoprism/api/__init__.py
photoprism/api/albums.py
photoprism/api/base.py
photoprism/api/config.py
photoprism/api/errors.py
photoprism/api/faces.py
photoprism/api/files.py
photoprism/api/labels.py
photoprism/api/library.py
photoprism/api/photos.py
photoprism/client.py
photoprism/exceptions.py
photoprism/models/__init__.py
photoprism/models/base.py
photoprism/models/config.py
photoprism/models/customize.py
photoprism/models/entity.py
photoprism/models/env.py
photoprism/models/form.py
photoprism/models/query.py
photoprism/models/search.py
photoprism/session.py
photoprism-0.1.0.dist-info/LICENSE
photoprism-0.1.0.dist-info/METADATA
photoprism-0.1.0.dist-info/WHEEL
photoprism-0.1.0.dist-info/RECORD
